README.rst
setup.py
kanban_simulator/__init__.py
kanban_simulator/board.py
kanban_simulator.egg-info/PKG-INFO
kanban_simulator.egg-info/SOURCES.txt
kanban_simulator.egg-info/dependency_links.txt
kanban_simulator.egg-info/top_level.txt