Metadata-Version: 1.0
Name: kanban-simulator
Version: 0.2
Summary: Simulate work flowing through a Kanban board
Home-page: https://github.com/optilude/kanban-simulator
Author: Martin Aspeli
Author-email: optilude@gmail.com
License: MIT
Keywords: agile kanban analytics
Platform: UNKNOWN
